inventree_cab/__init__.py
inventree_cab/cab_plugin.py
inventree_cab/cab_printer.py
inventree_cab/version.py
inventree_cab_plugin-0.1.0.dist-info/LICENSE
inventree_cab_plugin-0.1.0.dist-info/METADATA
inventree_cab_plugin-0.1.0.dist-info/WHEEL
inventree_cab_plugin-0.1.0.dist-info/entry_points.txt
inventree_cab_plugin-0.1.0.dist-info/top_level.txt
inventree_cab_plugin-0.1.0.dist-info/RECORD
