Metadata-Version: 2.1
Name: inventree-cab-plugin
Version: 0.1.0
Summary: Cab label printer plugin for InvenTree
Home-page: https://github.com/fturati/inventree-cab-plugin
Author: Florian Turati
Author-email: flo.turati@gmail.com
License: MIT
Keywords: inventree label printer printing inventory
Requires-Python: >=3.9
License-File: LICENSE
Requires-Dist: requests
Requires-Dist: Pillow
